naylence/__init__.py
naylence/__main__.py
naylence/cli/__init__.py
naylence/cli/commands/__init__.py
naylence/cli/commands/init.py
naylence/cli/main.py
naylence/starters/__init__.py
naylence/starters/github.py
naylence/starters/manifest.py
naylence/starters/models.py
naylence/utils/__init__.py
naylence/utils/fs.py
naylence/utils/names.py
naylence/utils/placeholders.py
naylence-0.1.0.dist-info/METADATA
naylence-0.1.0.dist-info/WHEEL
naylence-0.1.0.dist-info/entry_points.txt
naylence-0.1.0.dist-info/licenses/LICENSE
naylence-0.1.0.dist-info/RECORD
